wake/__init__.py
wake/cli.py
wake/wake.py
py_wake_cli-2.0.5.dist-info/LICENSE
py_wake_cli-2.0.5.dist-info/METADATA
py_wake_cli-2.0.5.dist-info/WHEEL
py_wake_cli-2.0.5.dist-info/entry_points.txt
py_wake_cli-2.0.5.dist-info/RECORD
