Metadata-Version: 2.1
Name: py-wake-cli
Version: 2.0.5
Summary: A simple wakeonlan implementation.
Home-page: https://github.com/lojoja/wake
License: MIT
Author: lojoja
Author-email: dev@lojoja.com
Requires-Python: >=3.10.0,<4.0.0
Classifier: Development Status :: 5 - Production/Stable
Classifier: License :: OSI Approved :: MIT License
Classifier: Programming Language :: Python :: 3
Classifier: Programming Language :: Python :: 3.10
Classifier: Programming Language :: Python :: 3.11
Classifier: Programming Language :: Python :: 3.12
Requires-Dist: click (>=8.0.0,<9.0.0)
Requires-Dist: clickext (>=1.0.1,<2.0.0)
Requires-Dist: tabulate (>=0.9.0,<0.10.0)
Project-URL: Bug Tracker, https://github.com/lojoja/wake/issues
Project-URL: Repository, https://github.com/lojoja/wake
